adapters/ChangeDNS.py
adapters/DNSRequests.py
adapters/HTTPRequests.py
adapters/__init__.py
awoc/__init__.py
awoc/datum/world.json
bin/__init__.py
bin/sentinelcli
bin/tun2socks
bin/v2ray
bin/warp-cli
bin/warp-svc
cli/__init__.py
cli/sentinel.py
cli/v2ray.py
cli/wallet.py
cli/warp.py
coin_api/__init__.py
coin_api/get_price.py
coin_api/scrtxxs.py
conf/__init__.py
conf/meile_config.py
conf/config/config.ini
fiat/__init__.py
fiat/fiat_interface.py
fiat/stripe_pay/__init__.py
fiat/stripe_pay/charge.py
fiat/stripe_pay/scrtsxx.py
fonts/Roboto-BoldItalic.ttf
fonts/__init__.py
fonts/mplus-2c-bold.ttf
geography/__init__.py
geography/continents.py
imgs/__init__.py
imgs/ad.png
imgs/ae.png
imgs/af.png
imgs/ag.png
imgs/ai.png
imgs/al.png
imgs/am.png
imgs/ao.png
imgs/aq.png
imgs/ar.png
imgs/as.png
imgs/at.png
imgs/atom.png
imgs/au.png
imgs/avg.png
imgs/aw.png
imgs/ax.png
imgs/az.png
imgs/ba.png
imgs/bb.png
imgs/bd.png
imgs/be.png
imgs/bf.png
imgs/bg.png
imgs/bh.png
imgs/bi.png
imgs/bj.png
imgs/bl.png
imgs/bm.png
imgs/bn.png
imgs/bo.png
imgs/bq.png
imgs/br.png
imgs/bs.png
imgs/bt.png
imgs/bv.png
imgs/bw.png
imgs/by.png
imgs/bz.png
imgs/ca.png
imgs/cc.png
imgs/cd.png
imgs/cf.png
imgs/cg.png
imgs/ch.png
imgs/ci.png
imgs/ck.png
imgs/cl.png
imgs/cm.png
imgs/cn.png
imgs/co.png
imgs/cr.png
imgs/cu.png
imgs/cv.png
imgs/cw.png
imgs/cx.png
imgs/cy.png
imgs/cz.png
imgs/de.png
imgs/dec.png
imgs/dj.png
imgs/dk.png
imgs/dm.png
imgs/do.png
imgs/dvpn.png
imgs/dz.png
imgs/ec.png
imgs/ee.png
imgs/eg.png
imgs/eh.png
imgs/er.png
imgs/es.png
imgs/et.png
imgs/fast.png
imgs/fastavg.png
imgs/fi.png
imgs/fj.png
imgs/fk.png
imgs/fm.png
imgs/fo.png
imgs/fr.png
imgs/ga.png
imgs/gb-eng.png
imgs/gb-nir.png
imgs/gb-sct.png
imgs/gb-wls.png
imgs/gb.png
imgs/gd.png
imgs/ge.png
imgs/gf.png
imgs/gg.png
imgs/gh.png
imgs/gi.png
imgs/gl.png
imgs/gm.png
imgs/gn.png
imgs/gp.png
imgs/gq.png
imgs/gr.png
imgs/gs.png
imgs/gt.png
imgs/gu.png
imgs/gw.png
imgs/gy.png
imgs/hk.png
imgs/hm.png
imgs/hn.png
imgs/hr.png
imgs/ht.png
meile_gui-0.15.0.1.dist-info/METADATA
meile_gui-0.15.0.1.dist-info/WHEEL
meile_gui-0.15.0.1.dist-info/entry_points.txt
meile_gui-0.15.0.1.dist-info/top_level.txt
meile_gui-0.15.0.1.dist-info/RECORD
