Metadata-Version: 2.1
Name: meile-gui
Version: 0.15.0.1
Summary: Meile dVPN powered by the Sentinel Network
Home-page: https://meile.app
Author: MathNodes
Author-email: freQniK@mathnodes.com
License: GNU General Public License (GPL)
Keywords: vpn,dvpn,sentinel,crypto,gui,privacy,security,decentralized
Classifier: Development Status :: 4 - Beta
Classifier: Programming Language :: Python
Classifier: Programming Language :: Python :: 3.10
Classifier: License :: OSI Approved :: GNU General Public License (GPL)
Classifier: Environment :: X11 Applications
Classifier: Environment :: MacOS X
Classifier: Intended Audience :: Information Technology
Classifier: Natural Language :: English
Classifier: Operating System :: MacOS
Classifier: Operating System :: POSIX
Classifier: Programming Language :: Python :: 3.10
Classifier: Topic :: System :: Networking
Classifier: Topic :: Internet
Requires-Dist: kivy ==2.2.0
Requires-Dist: kivymd
Requires-Dist: pydash
Requires-Dist: google-api-core ==2.11.1
Requires-Dist: treelib ==1.6.1
Requires-Dist: kivyoav
Requires-Dist: pexpect
Requires-Dist: qrcode
Requires-Dist: save-thread-result
Requires-Dist: screeninfo
Requires-Dist: mapview
Requires-Dist: psutil
Requires-Dist: unidecode
Requires-Dist: dnspython
Requires-Dist: cosmpy
Requires-Dist: sentinel-protobuf ==0.3.1
Requires-Dist: stripe
Requires-Dist: bip-utils
